pythinfer/__init__.py
pythinfer/cli.py
pythinfer/infer.py
pythinfer/inout.py
pythinfer/merge.py
pythinfer/py.typed
pythinfer/rdflibplus.py
pythinfer-0.3.0.dist-info/METADATA
pythinfer-0.3.0.dist-info/WHEEL
pythinfer-0.3.0.dist-info/entry_points.txt
pythinfer-0.3.0.dist-info/licenses/LICENSE.txt
pythinfer-0.3.0.dist-info/RECORD
