Metadata-Version: 2.4
Name: pythinfer
Version: 0.3.0
Summary: CLI to easily merge multiple RDF files and perform inference (OWL or SPARQL) on the result.
Author-email: Robert Muil <robertmuil@gmail.com>
License-Expression: Apache-2.0
License-File: LICENSE.txt
Keywords: Inference,Linked Data,OWL,RDF,SPARQL,Semantic Web
Classifier: Development Status :: 4 - Beta
Classifier: Environment :: Console
Classifier: Intended Audience :: Developers
Classifier: License :: OSI Approved :: Apache Software License
Classifier: Programming Language :: Python :: 3.12
Classifier: Programming Language :: Python :: 3.13
Classifier: Programming Language :: Python :: 3.14
Classifier: Topic :: Software Development :: Libraries :: Python Modules
Requires-Python: >=3.12
Requires-Dist: owlrl>=7.1.4
Requires-Dist: pydantic>=2.12.4
Requires-Dist: pyyaml>=6.0.3
Requires-Dist: rdflib>=7.4.0
Requires-Dist: typer>=0.20.0
